execflow/__init__.py
execflow/utils.py
execflow/strategies/aiida_shell_dlite_func.py
execflow/strategies/aiida_shell_func.py
execflow/wrapper/__init__.py
execflow/wrapper/calculations/parse_pipeline.py
execflow/wrapper/calculations/update_session.py
execflow/wrapper/data/README.md
execflow/wrapper/data/__init__.py
execflow/wrapper/data/base.py
execflow/wrapper/data/declarative_pipeline.py
execflow/wrapper/data/filterconfig.py
execflow/wrapper/data/functionconfig.py
execflow/wrapper/data/genericconfig.py
execflow/wrapper/data/mappingconfig.py
execflow/wrapper/data/resourceconfig.py
execflow/wrapper/data/secretconfig.py
execflow/wrapper/data/transformationconfig.py
execflow/wrapper/strategies/__init__.py
execflow/wrapper/strategies/dataresource.py
execflow/wrapper/strategies/filter.py
execflow/wrapper/strategies/function.py
execflow/wrapper/strategies/mapping.py
execflow/wrapper/strategies/transformation.py
execflow/wrapper/workflows/__init__.py
execflow/wrapper/workflows/pipeline.py
execflowsdk-0.3.0.dist-info/entry_points.txt
execflowsdk-0.3.0.dist-info/LICENSE
execflowsdk-0.3.0.dist-info/WHEEL
execflowsdk-0.3.0.dist-info/METADATA
execflowsdk-0.3.0.dist-info/RECORD
