Metadata-Version: 2.1
Name: ExecFlowSDK
Version: 0.3.0
Summary: OpenModel Wrapper Software Development Kit (SDK).
Keywords: AiiDA,OTE,OTEAPI
Author-email: SINTEF <Team4.0@SINTEF.no>
Requires-Python: ~=3.9
Classifier: Development Status :: 2 - Pre-Alpha
Classifier: License :: OSI Approved :: MIT License
Classifier: Programming Language :: Python :: 3
Classifier: Programming Language :: Python :: 3.9
Classifier: Programming Language :: Python :: 3.10
Classifier: Framework :: AiiDA
Classifier: Natural Language :: English
Classifier: Operating System :: OS Independent
Requires-Dist: aiida-core >=2.2.1,<3
Requires-Dist: aiida-pseudo ~=1.0.0
Requires-Dist: aiida-shell ~=0.3.0
Requires-Dist: oteapi-core ~=0.3.0
Requires-Dist: oteapi-dlite ~=0.1.1
Requires-Dist: myst-nb ~=0.17.1 ; extra == "dev"
Requires-Dist: Sphinx >=4.5.0,<6 ; extra == "dev"
Requires-Dist: sphinx-autoapi ~=2.0 ; extra == "dev"
Requires-Dist: sphinx-autobuild ==2021.3.14 ; extra == "dev"
Requires-Dist: sphinx-book-theme ~=0.3.3 ; extra == "dev"
Requires-Dist: sphinx-copybutton ~=0.5.1 ; extra == "dev"
Requires-Dist: sphinx-design ~=0.3.0 ; extra == "dev"
Requires-Dist: sphinxcontrib-plantuml ~=0.24.1 ; extra == "dev"
Requires-Dist: pgtest ~=1.3,>=1.3.1 ; extra == "dev"
Requires-Dist: pre-commit ~=3.0 ; extra == "dev"
Requires-Dist: pylint ~=2.16 ; extra == "dev"
Requires-Dist: pytest ~=7.2 ; extra == "dev"
Requires-Dist: pytest-cov ~=4.0 ; extra == "dev"
Requires-Dist: myst-nb ~=0.17.1 ; extra == "docs"
Requires-Dist: Sphinx >=4.5.0,<6 ; extra == "docs"
Requires-Dist: sphinx-autoapi ~=2.0 ; extra == "docs"
Requires-Dist: sphinx-autobuild ==2021.3.14 ; extra == "docs"
Requires-Dist: sphinx-book-theme ~=0.3.3 ; extra == "docs"
Requires-Dist: sphinx-copybutton ~=0.5.1 ; extra == "docs"
Requires-Dist: sphinx-design ~=0.3.0 ; extra == "docs"
Requires-Dist: sphinxcontrib-plantuml ~=0.24.1 ; extra == "docs"
Requires-Dist: pgtest ~=1.3,>=1.3.1 ; extra == "testing"
Requires-Dist: pre-commit ~=3.0 ; extra == "testing"
Requires-Dist: pylint ~=2.16 ; extra == "testing"
Requires-Dist: pytest ~=7.2 ; extra == "testing"
Requires-Dist: pytest-cov ~=4.0 ; extra == "testing"
Project-URL: Changelog, https://github.com/H2020-OpenModel/WP3-WrapperSDK/blob/main/CHANGELOG.md
Project-URL: Documentation, https://H2020-OpenModel.github.io/WP3-WrapperSDK
Project-URL: Home, https://github.com/H2020-OpenModel/WP3-WrapperSDK
Project-URL: Issue Tracker, https://github.com/H2020-OpenModel/WP3-WrapperSDK/issues
Project-URL: Package, https://pypi.org/project/ExecFlowSDK
Project-URL: Source, https://github.com/H2020-OpenModel/WP3-WrapperSDK
Provides-Extra: dev
Provides-Extra: docs
Provides-Extra: testing
